{
  "operationId": "getBucket",
  "method": "GET",
  "path": "/n/{namespaceName}/b/{bucketName}",
  "summary": "Oracle Cloud Get Bucket",
  "requestExamples": [],
  "responseExamples": [
    {
      "status": "200",
      "contentType": "application/json",
      "name": "GetBucket200Example",
      "example": {
        "namespace": "my-namespace",
        "name": "my-bucket",
        "compartmentId": "ocid1.compartment.oc1..abcdefg123456",
        "createdBy": "example-value",
        "timeCreated": "2026-04-18T10:30:00Z",
        "publicAccessType": "NoPublicAccess",
        "storageTier": "Standard",
        "objectEventsEnabled": false,
        "freeformTags": {
          "key1": "value1"
        },
        "definedTags": {
          "key1": "value1"
        },
        "objectLifecyclePolicyEtag": "example-value",
        "approximateCount": 1500,
        "approximateSize": 1073741824,
        "versioning": "Enabled"
      }
    },
    {
      "status": "404",
      "contentType": "application/json",
      "name": "GetBucket404Example",
      "example": {
        "code": "BucketNotFound",
        "message": "The bucket does not exist.",
        "status": 404
      }
    }
  ]
}